odoo/addons/stock_operating_unit_access_all/README.rst
odoo/addons/stock_operating_unit_access_all/__init__.py
odoo/addons/stock_operating_unit_access_all/__manifest__.py
odoo/addons/stock_operating_unit_access_all/i18n/it.po
odoo/addons/stock_operating_unit_access_all/i18n/stock_operating_unit_access_all.pot
odoo/addons/stock_operating_unit_access_all/readme/CONFIGURE.md
odoo/addons/stock_operating_unit_access_all/readme/CONTRIBUTORS.md
odoo/addons/stock_operating_unit_access_all/readme/DESCRIPTION.md
odoo/addons/stock_operating_unit_access_all/security/stock_security.xml
odoo/addons/stock_operating_unit_access_all/static/description/icon.png
odoo/addons/stock_operating_unit_access_all/static/description/index.html
odoo_addon_stock_operating_unit_access_all-18.0.1.0.0.1.dist-info/METADATA
odoo_addon_stock_operating_unit_access_all-18.0.1.0.0.1.dist-info/WHEEL
odoo_addon_stock_operating_unit_access_all-18.0.1.0.0.1.dist-info/top_level.txt
odoo_addon_stock_operating_unit_access_all-18.0.1.0.0.1.dist-info/RECORD
